cloudx/__init__.py
cloudx/cloudx.py
cloudx/common.py
cloudx/methods.py
cloudx/py.typed
cloudx/asgi/__init__.py
cloudx/asgi/core.py
cloudx/asgi/request.py
cloudx/asgi/response.py
cloudx/asgi/router.py
cloudx/cli/__init__.py
cloudx/middlewares/__init__.py
cloudx/middlewares/aws_lambda.py
cloudx/middlewares/aws_lambda_extensions.py
cloudx/plugins/__init__.py
cloudx/plugins/base.py
cloudx/plugins/finder.py
cloudx/plugins/loader.py
cloudx/plugins/types.py
cloudx/utils/__init__.py
cloudx/utils/asyncify.py
cloudx/utils/bootstrap.py
cloudx/utils/container.py
cloudx/utils/inject.py
cloudx/utils/logger.py
cloudx/utils/serializator.py
cloudx/utils/teardown.py
cloudx_oss-4.0.2.dist-info/licenses/LICENSE
cloudx_oss-4.0.2.dist-info/METADATA
cloudx_oss-4.0.2.dist-info/WHEEL
cloudx_oss-4.0.2.dist-info/entry_points.txt
cloudx_oss-4.0.2.dist-info/top_level.txt
cloudx_oss-4.0.2.dist-info/RECORD
