Metadata-Version: 2.4
Name: cloudx-oss
Version: 4.0.2
Summary: Fast, simple and lightweight ASGI framework for building cloud native microservices
Author-email: Haim Shulner <haim.shulner@gmail.com>
Classifier: Programming Language :: Python :: 3
Classifier: Operating System :: OS Independent
Classifier: Typing :: Typed
Requires-Python: >=3.7
License-File: LICENSE
Dynamic: license-file
